{
  "name": "mitigation_sectoralcbs",
  "data": [
    {
      "seriesName": "FT_RSD",
      "seriesValues": [
        [
          2018,
          0.002385319890716415
        ],
        [
          2019,
          0.01414236159639245
        ],
        [
          2020,
          0.021754060222972063
        ],
        [
          2021,
          0.026967900209871647
        ],
        [
          2022,
          0.1960875241474052
        ],
        [
          2023,
          0.1968911356350604
        ],
        [
          2024,
          0.19689116274196158
        ],
        [
          2025,
          0.19689116252604189
        ],
        [
          2026,
          0.1951669995327135
        ],
        [
          2027,
          0.1951669801357472
        ],
        [
          2028,
          0.1951669566048878
        ],
        [
          2029,
          0.1921627363913102
        ],
        [
          2030,
          0.1914801137252595
        ],
        [
          2031,
          0.1951669445784828
        ],
        [
          2032,
          0.1951669384781936
        ],
        [
          2033,
          0.1951669315015331
        ],
        [
          2034,
          0.1951668876477417
        ],
        [
          2035,
          0.2619063235782856
        ],
        [
          2036,
          0.368394080258653
        ],
        [
          2037,
          0.3789753812187674
        ],
        [
          2038,
          0.3896304790108479
        ],
        [
          2039,
          0.3959552208983606
        ],
        [
          2040,
          0.4022686098511271
        ],
        [
          2041,
          0.420884156902909
        ],
        [
          2042,
          0.4208841398350307
        ],
        [
          2043,
          0.4208841406674107
        ],
        [
          2044,
          0.4273454728402004
        ],
        [
          2045,
          0.4338315246377822
        ],
        [
          2046,
          2.6750536451165825
        ],
        [
          2047,
          2.6750538495941942
        ],
        [
          2048,
          2.6750538314550045
        ],
        [
          2049,
          2.67505383705761
        ],
        [
          2050,
          2.675053780680549
        ],
        [
          2051,
          2.6750537483798063
        ]
      ]
    },
    {
      "seriesName": "FT_SRV",
      "seriesValues": [
        [
          2021,
          0.3230321185432535
        ],
        [
          2022,
          0.1531088764570502
        ],
        [
          2023,
          0.1531088753146321
        ],
        [
          2024,
          0.1531088665542274
        ],
        [
          2025,
          0.1531088766389789
        ],
        [
          2026,
          2.407279054663393
        ],
        [
          2027,
          2.40727906772713
        ],
        [
          2028,
          2.4072790737512335
        ],
        [
          2029,
          2.4072790785197027
        ],
        [
          2030,
          2.4072790778594477
        ],
        [
          2031,
          2.4072790498221783
        ],
        [
          2032,
          2.407279049357272
        ],
        [
          2033,
          2.4072790490053277
        ],
        [
          2034,
          2.4072790676712423
        ],
        [
          2035,
          2.3599489794289576
        ],
        [
          2036,
          2.306643502126105
        ],
        [
          2037,
          2.2960756004570215
        ],
        [
          2038,
          2.2854232485823034
        ],
        [
          2039,
          2.279099149591205
        ],
        [
          2040,
          2.272785755458588
        ],
        [
          2041,
          2.254170184332247
        ],
        [
          2042,
          2.2541701861646195
        ],
        [
          2043,
          2.2541701803112955
        ],
        [
          2044,
          2.2477088603411843
        ],
        [
          2045,
          2.2412227991254823
        ],
        [
          2046,
          3.401010116788515e-07
        ],
        [
          2047,
          2.867968036440926e-07
        ],
        [
          2048,
          3.127409685938555e-07
        ],
        [
          2049,
          3.146438815877508e-07
        ],
        [
          2050,
          3.390796843861395e-07
        ],
        [
          2051,
          3.353612058636992e-07
        ]
      ]
    }
  ]
}