{
  "name": "mitigation_sectoralcbs",
  "data": [
    {
      "seriesName": "SRVELC",
      "seriesValues": [
        [
          2018,
          3.7411641755696636
        ],
        [
          2019,
          8.293776371712077
        ],
        [
          2020,
          10.600073875380037
        ],
        [
          2021,
          9.17219972754994
        ],
        [
          2022,
          17.037841115218534
        ],
        [
          2023,
          15.355529701562785
        ],
        [
          2024,
          12.775204596835945
        ],
        [
          2025,
          10.523567493771077
        ],
        [
          2026,
          19.36912718273717
        ],
        [
          2027,
          19.77342850034435
        ],
        [
          2028,
          20.18614709859059
        ],
        [
          2029,
          20.60745815488795
        ],
        [
          2030,
          20.607533896154095
        ],
        [
          2031,
          14.743536661120201
        ],
        [
          2032,
          9.566974011168329
        ],
        [
          2033,
          4.510279444061567
        ],
        [
          2034,
          7.4187268866428315
        ],
        [
          2035,
          7.692672391274212
        ],
        [
          2036,
          19.28625140475729
        ],
        [
          2037,
          22.092861502858973
        ],
        [
          2038,
          22.097200088240296
        ],
        [
          2039,
          22.299818333255516
        ],
        [
          2040,
          22.503049583465923
        ],
        [
          2041,
          22.706903350663993
        ],
        [
          2042,
          22.86641221630442
        ],
        [
          2043,
          23.026094741239433
        ],
        [
          2044,
          22.28240138499377
        ],
        [
          2045,
          22.29081983414568
        ],
        [
          2046,
          22.451064778680255
        ],
        [
          2047,
          22.593765619953693
        ],
        [
          2048,
          22.7464074055193
        ],
        [
          2049,
          22.895482116436686
        ],
        [
          2050,
          22.320410806812177
        ],
        [
          2051,
          22.486933101519533
        ]
      ]
    },
    {
      "seriesName": "SRVGAS",
      "seriesValues": [
        [
          2018,
          3.4183039618876
        ],
        [
          2019,
          3.503345069322875
        ],
        [
          2020,
          1.2851343661400203
        ],
        [
          2021,
          3.3806955386281143
        ],
        [
          2023,
          2.8654581144435025
        ],
        [
          2024,
          6.9015136470116225
        ],
        [
          2025,
          10.526736532969126
        ],
        [
          2030,
          0.5492463777178465
        ],
        [
          2031,
          8.600102894278034
        ],
        [
          2032,
          15.55576856453132
        ],
        [
          2033,
          22.37907544709858
        ],
        [
          2034,
          18.998399987687268
        ],
        [
          2035,
          18.99839417052599
        ],
        [
          2036,
          3.3379459434744065
        ],
        [
          2037,
          2.3148668844622566e-06
        ],
        [
          2038,
          1.4127779159444192e-06
        ],
        [
          2039,
          1.012347253756797e-06
        ],
        [
          2040,
          9.14680528691992e-07
        ],
        [
          2041,
          6.807995392441254e-07
        ],
        [
          2042,
          6.474770774506206e-07
        ],
        [
          2043,
          5.87463017942171e-07
        ],
        [
          2044,
          5.393982737611332e-07
        ],
        [
          2045,
          4.994028830139408e-07
        ],
        [
          2046,
          4.71047655644882e-07
        ],
        [
          2047,
          4.474351494668478e-07
        ],
        [
          2048,
          4.253299707732664e-07
        ],
        [
          2049,
          4.152753833658596e-07
        ],
        [
          2050,
          5.597701146784054e-07
        ],
        [
          2051,
          9.335374706937835e-07
        ]
      ]
    },
    {
      "seriesName": "SRVLPG",
      "seriesValues": [
        [
          2018,
          2.9527159895861397
        ],
        [
          2019,
          5.999999619680784
        ],
        [
          2020,
          5.599999860600212
        ],
        [
          2021,
          5.999999986764519
        ],
        [
          2031,
          1.845571067921637e-06
        ],
        [
          2032,
          8.673420986859742e-07
        ],
        [
          2033,
          7.7517299457983e-07
        ],
        [
          2034,
          6.746446985981428e-07
        ],
        [
          2035,
          5.751185256011332e-07
        ],
        [
          2036,
          5.766734783788192e-07
        ],
        [
          2037,
          4.859016193866892e-07
        ],
        [
          2038,
          4.468414867356e-07
        ],
        [
          2039,
          4.117421142001396e-07
        ],
        [
          2040,
          4.081267567706596e-07
        ],
        [
          2041,
          3.584227545054674e-07
        ],
        [
          2042,
          3.53189577444389e-07
        ],
        [
          2043,
          3.386398875768632e-07
        ],
        [
          2044,
          3.25616314432341e-07
        ],
        [
          2045,
          3.13799017953389e-07
        ],
        [
          2046,
          3.0520120724993077e-07
        ],
        [
          2051,
          9.397056198666576e-07
        ]
      ]
    }
  ]
}