{
  "name": "mitigation_sectoralcbs-led_halfway",
  "data": [
    {
      "seriesName": "INDBDL",
      "seriesValues": [
        [
          2019,
          0.0069410026281036
        ],
        [
          2022,
          0.0254583086437725
        ],
        [
          2023,
          0.0409537390233338
        ],
        [
          2024,
          0.0561291559290101
        ],
        [
          2025,
          0.0709845590142419
        ],
        [
          2026,
          0.085519913593904
        ],
        [
          2031,
          1.7288589961207655e-05
        ],
        [
          2032,
          0.1023576887378076
        ],
        [
          2033,
          0.1903691667750425
        ],
        [
          2034,
          0.2070922628303619
        ],
        [
          2035,
          0.2238577746737801
        ],
        [
          2036,
          0.24066620025529228
        ],
        [
          2037,
          0.2575176518862026
        ],
        [
          2038,
          0.2744120374491612
        ],
        [
          2039,
          0.2913498398649344
        ],
        [
          2040,
          0.308330591058173
        ],
        [
          2041,
          0.3253543141806183
        ],
        [
          2042,
          0.34242106882760703
        ],
        [
          2043,
          0.3595308913123622
        ],
        [
          2044,
          0.3766835662938348
        ],
        [
          2045,
          0.3938796388536026
        ],
        [
          2046,
          0.4111185536004842
        ],
        [
          2047,
          0.4284005463095354
        ],
        [
          2048,
          0.4457256565051429
        ],
        [
          2049,
          0.4630937763552677
        ],
        [
          2050,
          0.4805045591908314
        ],
        [
          2051,
          0.48050392366683653
        ],
        [
          2052,
          0.4805039744091449
        ]
      ]
    },
    {
      "seriesName": "INDBIO",
      "seriesValues": [
        [
          2019,
          0.0458103902301235
        ],
        [
          2020,
          0.0461891378746522
        ],
        [
          2021,
          0.1057074411283315
        ],
        [
          2022,
          0.4724263358306095
        ],
        [
          2023,
          0.694558207438848
        ],
        [
          2024,
          0.912080627983925
        ],
        [
          2025,
          1.1249935965310827
        ],
        [
          2026,
          1.3332971133211704
        ],
        [
          2027,
          1.5369911188170176
        ],
        [
          2028,
          1.7086994894472185
        ],
        [
          2029,
          1.8783080949117938
        ],
        [
          2030,
          2.05164768784786
        ],
        [
          2031,
          2.3595513673155137
        ],
        [
          2032,
          2.59930649947644
        ],
        [
          2033,
          2.839681700257519
        ],
        [
          2034,
          3.0806770292255496
        ],
        [
          2035,
          3.3222925064487834
        ],
        [
          2036,
          3.564528101671787
        ],
        [
          2037,
          3.8073838276797805
        ],
        [
          2038,
          4.050859699920825
        ],
        [
          2039,
          4.294955545252924
        ],
        [
          2040,
          4.539671662444065
        ],
        [
          2041,
          4.785007896855799
        ],
        [
          2042,
          5.030964240282833
        ],
        [
          2043,
          5.27754067694891
        ],
        [
          2044,
          5.524737277611094
        ],
        [
          2045,
          5.772553801316494
        ],
        [
          2046,
          6.020990646108363
        ],
        [
          2047,
          6.270047723230249
        ],
        [
          2048,
          6.519724872960913
        ],
        [
          2049,
          6.770022136593405
        ],
        [
          2050,
          7.020939159563104
        ],
        [
          2051,
          5.337131507442308
        ],
        [
          2052,
          5.337130733165682
        ]
      ]
    },
    {
      "seriesName": "INDBKE",
      "seriesValues": [
        [
          2019,
          0.000520649885649997
        ],
        [
          2022,
          0.0020002253682661337
        ],
        [
          2023,
          0.0032176847356870093
        ],
        [
          2024,
          0.004410000883372
        ],
        [
          2025,
          0.005577173916212789
        ],
        [
          2026,
          0.0067192035320138965
        ],
        [
          2031,
          0.01233580469224117
        ],
        [
          2032,
          0.013644791823911208
        ],
        [
          2033,
          0.014955891325519634
        ],
        [
          2034,
          0.0162700599430095
        ],
        [
          2035,
          0.0175874863114009
        ],
        [
          2036,
          0.0189082421836163
        ],
        [
          2037,
          0.020232339863412
        ],
        [
          2038,
          0.0215597955204939
        ],
        [
          2039,
          0.0228906178954632
        ],
        [
          2040,
          0.0242248118644714
        ],
        [
          2041,
          0.0255623902159616
        ],
        [
          2042,
          0.0269033417841461
        ],
        [
          2043,
          0.0282476693180225
        ],
        [
          2044,
          0.029595374642091398
        ],
        [
          2045,
          0.030946458853324102
        ],
        [
          2046,
          0.0323009225870597
        ],
        [
          2047,
          0.0336587666529578
        ],
        [
          2048,
          0.035019991393262104
        ],
        [
          2049,
          0.036384596836695704
        ],
        [
          2050,
          0.0377523848027113
        ],
        [
          2051,
          1.0377850537992609e-06
        ],
        [
          2052,
          1.152285316686583e-06
        ]
      ]
    },
    {
      "seriesName": "INDCOA",
      "seriesValues": [
        [
          2019,
          3.2648590267106004
        ],
        [
          2020,
          3.0253124710909916
        ],
        [
          2021,
          3.654122221198441
        ],
        [
          2022,
          3.617741864353409
        ],
        [
          2023,
          3.581361569347261
        ],
        [
          2024,
          3.5449812744913025
        ],
        [
          2025,
          3.5086009792653883
        ],
        [
          2026,
          3.472220684613376
        ],
        [
          2027,
          3.4358404041635833
        ],
        [
          2028,
          3.3994601092761645
        ],
        [
          2029,
          3.363079814325022
        ],
        [
          2030,
          3.326699456986155
        ],
        [
          2031,
          3.331069330156985
        ],
        [
          2032,
          3.335439318934331
        ],
        [
          2033,
          3.339809293342386
        ],
        [
          2034,
          3.3441792782712705
        ],
        [
          2035,
          3.348549243442152
        ],
        [
          2036,
          3.3529192268792607
        ],
        [
          2037,
          3.3572892122960702
        ],
        [
          2038,
          3.361659194654908
        ],
        [
          2039,
          3.283914141311728
        ],
        [
          2040,
          2.9892519756761304
        ],
        [
          2041,
          2.6938147668957346
        ],
        [
          2042,
          2.397603060366102
        ],
        [
          2043,
          2.10061558104853
        ],
        [
          2044,
          1.8028531026673786
        ],
        [
          2045,
          1.5043156944603915
        ],
        [
          2046,
          1.205002977004954
        ],
        [
          2047,
          0.9049149736179161
        ],
        [
          2048,
          0.6040518869869769
        ],
        [
          2049,
          0.3024136857118698
        ],
        [
          2050,
          7.203361563092274e-07
        ],
        [
          2051,
          3.41409785053986
        ],
        [
          2052,
          3.414097523815398
        ]
      ]
    },
    {
      "seriesName": "INDCOK",
      "seriesValues": [
        [
          2019,
          5.274964102686879
        ],
        [
          2020,
          4.783848557442163
        ],
        [
          2021,
          5.605560942777416
        ],
        [
          2022,
          5.090306051457735
        ],
        [
          2023,
          4.755514257762787
        ],
        [
          2024,
          4.426484278352048
        ],
        [
          2025,
          4.1032161107472405
        ],
        [
          2026,
          3.7857097631175147
        ],
        [
          2027,
          3.4749843265301967
        ],
        [
          2028,
          3.196366596001253
        ],
        [
          2029,
          2.9210012445788647
        ],
        [
          2030,
          3.1488556157379746
        ],
        [
          2031,
          2.7840144029189373
        ],
        [
          2032,
          2.3650858707463485
        ],
        [
          2033,
          1.6948092107884256
        ],
        [
          2034,
          1.4004260936538224
        ],
        [
          2035,
          1.105268844419796
        ],
        [
          2036,
          0.8093383180147324
        ],
        [
          2037,
          0.513622184602957
        ],
        [
          2038,
          0.21614075689958148
        ]
      ]
    },
    {
      "seriesName": "INDDST",
      "seriesValues": [
        [
          2019,
          0.4877766755511736
        ],
        [
          2020,
          0.4620541660595582
        ],
        [
          2021,
          0.5142865408723297
        ],
        [
          2022,
          0.4837080156883107
        ],
        [
          2023,
          0.4630923693350557
        ],
        [
          2024,
          0.44279673641033
        ],
        [
          2025,
          0.4228211173110034
        ],
        [
          2026,
          0.403165546691675
        ],
        [
          2027,
          0.4835651656195236
        ],
        [
          2028,
          0.47844495977639423
        ],
        [
          2029,
          0.4733247263616835
        ],
        [
          2030,
          0.4682044204111929
        ],
        [
          2031,
          0.4688022969245479
        ],
        [
          2032,
          0.3670769337756578
        ],
        [
          2033,
          0.2796804937063544
        ],
        [
          2034,
          0.2635724352717447
        ],
        [
          2035,
          0.2474219607685818
        ],
        [
          2036,
          0.231228573118829
        ],
        [
          2037,
          0.2149921638644191
        ],
        [
          2038,
          0.19871281635103522
        ],
        [
          2039,
          0.1823900439695203
        ],
        [
          2040,
          0.1660243315841061
        ],
        [
          2041,
          0.1496156537530161
        ],
        [
          2042,
          0.1331639459396202
        ],
        [
          2043,
          0.116669166381691
        ],
        [
          2044,
          0.1001315329551396
        ],
        [
          2045,
          0.083550499713813
        ],
        [
          2046,
          0.06692662158133669
        ],
        [
          2047,
          0.0502596653469491
        ],
        [
          2048,
          0.0335495895850413
        ],
        [
          2049,
          0.016796506346608
        ],
        [
          2050,
          7.52639338698373e-07
        ],
        [
          2051,
          1.327091882841506e-06
        ],
        [
          2052,
          1.2689925885495427e-06
        ]
      ]
    },
    {
      "seriesName": "INDELC",
      "seriesValues": [
        [
          2019,
          2.593087664906186
        ],
        [
          2020,
          2.46326255880275
        ],
        [
          2021,
          2.5333708091267946
        ],
        [
          2022,
          2.5081486660058756
        ],
        [
          2023,
          2.482926528279627
        ],
        [
          2024,
          2.4577043908251537
        ],
        [
          2025,
          2.4324822534878128
        ],
        [
          2026,
          2.4072601142608194
        ],
        [
          2027,
          2.381020516361816
        ],
        [
          2028,
          2.3558091247365107
        ],
        [
          2029,
          2.330597769266413
        ],
        [
          2030,
          2.305386498361683
        ],
        [
          2031,
          2.3094005800318786
        ],
        [
          2032,
          2.3124303742634846
        ],
        [
          2033,
          2.3154600399669505
        ],
        [
          2034,
          2.318489578230991
        ],
        [
          2035,
          2.3215191332885117
        ],
        [
          2036,
          2.324546892921728
        ],
        [
          2037,
          2.3265849702006256
        ],
        [
          2038,
          2.329613350379395
        ],
        [
          2039,
          2.3326417023854207
        ],
        [
          2040,
          2.335670012244357
        ],
        [
          2041,
          2.338698480589154
        ],
        [
          2042,
          2.341726776591913
        ],
        [
          2043,
          2.3447551355401997
        ],
        [
          2044,
          2.3477835439719352
        ],
        [
          2045,
          2.3508119857584724
        ],
        [
          2046,
          2.3538403756491366
        ],
        [
          2047,
          2.3568687700706388
        ],
        [
          2048,
          2.3598972042144992
        ],
        [
          2049,
          2.362925585053257
        ],
        [
          2050,
          2.365953999980976
        ],
        [
          2051,
          2.3659538167877403
        ],
        [
          2052,
          2.365954004629209
        ]
      ]
    },
    {
      "seriesName": "INDGAS",
      "seriesValues": [
        [
          2019,
          1.326766513160695
        ],
        [
          2020,
          1.2391672969136693
        ],
        [
          2021,
          1.3792475939263014
        ],
        [
          2022,
          1.3189431804212843
        ],
        [
          2023,
          1.2774987166299976
        ],
        [
          2024,
          1.2359227204657166
        ],
        [
          2025,
          1.1925913927598564
        ],
        [
          2026,
          1.1380341542770394
        ],
        [
          2027,
          1.2968569748034666
        ],
        [
          2028,
          1.2831253717397233
        ],
        [
          2029,
          1.2693936380775324
        ],
        [
          2030,
          1.255661750813275
        ],
        [
          2031,
          0.9950503233392961
        ],
        [
          2032,
          0.9773968244097264
        ],
        [
          2033,
          0.9520590226223821
        ],
        [
          2034,
          0.9283495269654416
        ],
        [
          2035,
          0.9102226492818031
        ],
        [
          2036,
          0.8933000155293156
        ],
        [
          2037,
          0.8743923479108221
        ],
        [
          2038,
          0.840236135720095
        ],
        [
          2039,
          0.8083966996634306
        ],
        [
          2040,
          0.7875300192687482
        ],
        [
          2041,
          0.7676823082542142
        ],
        [
          2042,
          0.7490586275244991
        ],
        [
          2043,
          0.731079614557846
        ],
        [
          2044,
          0.7138469666880813
        ],
        [
          2045,
          0.6974142645347097
        ],
        [
          2046,
          0.6813115476269054
        ],
        [
          2047,
          0.6649061183875496
        ],
        [
          2048,
          0.6524909059174517
        ],
        [
          2049,
          0.6404753984964308
        ],
        [
          2050,
          0.6312182796682921
        ],
        [
          2051,
          0.68073426982895
        ],
        [
          2052,
          0.6407241994719753
        ]
      ]
    },
    {
      "seriesName": "INDH2G",
      "seriesValues": [
        [
          2019,
          0.2143615104683211
        ],
        [
          2020,
          0.21436281536611249
        ],
        [
          2022,
          0.091674933373138
        ],
        [
          2023,
          0.147473700023334
        ],
        [
          2024,
          0.2021201036902495
        ],
        [
          2025,
          0.2556141477451256
        ],
        [
          2026,
          0.3079558255751484
        ],
        [
          2027,
          0.3591437266928641
        ],
        [
          2028,
          0.4091811558123643
        ],
        [
          2029,
          0.4580659703657595
        ],
        [
          2031,
          0.0627829071907773
        ],
        [
          2032,
          0.2487863533805606
        ],
        [
          2033,
          0.6855179610475237
        ],
        [
          2034,
          0.7457360235372201
        ],
        [
          2035,
          0.8061080623236812
        ],
        [
          2036,
          0.8666350281563264
        ],
        [
          2037,
          0.9273170791995543
        ],
        [
          2038,
          0.9881541016101533
        ],
        [
          2039,
          1.0491453725667383
        ],
        [
          2040,
          1.1102928762626842
        ],
        [
          2041,
          1.1715952979424398
        ],
        [
          2042,
          1.23305209523008
        ],
        [
          2043,
          1.2946645641991945
        ],
        [
          2044,
          1.3564318577713292
        ],
        [
          2045,
          1.4183541589793498
        ],
        [
          2046,
          1.4804314367025009
        ],
        [
          2047,
          1.5426637691724978
        ],
        [
          2048,
          1.6050511070777729
        ],
        [
          2049,
          1.6675934804755086
        ],
        [
          2050,
          1.7302908199035962
        ],
        [
          2051,
          1.3378344229344693e-06
        ],
        [
          2052,
          2.4368419263032305e-06
        ]
      ]
    },
    {
      "seriesName": "INDKER",
      "seriesValues": [
        [
          2019,
          0.0383487849426818
        ],
        [
          2020,
          0.0339825794761395
        ],
        [
          2021,
          0.040406939787167404
        ],
        [
          2022,
          0.038004424043087896
        ],
        [
          2023,
          0.0363846748180986
        ],
        [
          2024,
          0.0347900688119657
        ],
        [
          2025,
          0.033220605920801304
        ],
        [
          2026,
          0.0316762864246708
        ],
        [
          2027,
          0.0379929570100782
        ],
        [
          2028,
          0.0375906589598377
        ],
        [
          2029,
          0.0371883596423066
        ],
        [
          2030,
          0.036785793825162956
        ],
        [
          2031,
          0.0244988380500359
        ],
        [
          2032,
          0.0232381736153428
        ],
        [
          2033,
          0.0219753969642666
        ],
        [
          2034,
          0.0207095512384102
        ],
        [
          2035,
          0.019440447740783
        ],
        [
          2036,
          0.0181680147117991
        ],
        [
          2037,
          0.0168922443239367
        ],
        [
          2038,
          0.0156131116424604
        ],
        [
          2039,
          0.0143306122239848
        ],
        [
          2040,
          0.0130447429527043
        ],
        [
          2041,
          0.011755486275036
        ],
        [
          2042,
          0.0104628599550361
        ],
        [
          2043,
          0.0091668555844134
        ],
        [
          2044,
          0.007867472866951388
        ],
        [
          2045,
          0.00656471048542571
        ],
        [
          2046,
          0.005258569157571429
        ],
        [
          2047,
          0.00394904733626713
        ],
        [
          2048,
          0.0026361428330566117
        ],
        [
          2049,
          0.0013198600959928755
        ],
        [
          2051,
          0.0377517420317223
        ],
        [
          2052,
          0.037751624418318
        ]
      ]
    },
    {
      "seriesName": "INDLPG",
      "seriesValues": [
        [
          2019,
          0.0954383282031055
        ],
        [
          2020,
          0.0839507054015797
        ],
        [
          2021,
          0.0948841531275978
        ],
        [
          2022,
          0.093939475652804
        ],
        [
          2023,
          0.0929948128389659
        ],
        [
          2024,
          0.0920501500262678
        ],
        [
          2025,
          0.0911054872144031
        ],
        [
          2026,
          0.0901608238390275
        ],
        [
          2027,
          0.0892161141253063
        ],
        [
          2028,
          0.0882714580598805
        ],
        [
          2029,
          0.0873267844518259
        ],
        [
          2030,
          0.08638206184817769
        ],
        [
          2031,
          0.0864955217006797
        ],
        [
          2032,
          0.0866089921791068
        ],
        [
          2033,
          0.0867224632565389
        ],
        [
          2034,
          0.0868359345197602
        ],
        [
          2035,
          0.0869494056704992
        ],
        [
          2036,
          0.0870628765694351
        ],
        [
          2037,
          0.08717639415908571
        ],
        [
          2038,
          0.0872898684854134
        ],
        [
          2039,
          0.0874033425642836
        ],
        [
          2040,
          0.0875168542172861
        ],
        [
          2041,
          0.0876302904625134
        ],
        [
          2042,
          0.0877438083454521
        ],
        [
          2043,
          0.0878572809567463
        ],
        [
          2044,
          0.087970738488277
        ],
        [
          2045,
          0.088084183495104
        ],
        [
          2046,
          0.0881976479060293
        ],
        [
          2047,
          0.0883111097301287
        ],
        [
          2048,
          0.088424544181815
        ],
        [
          2049,
          0.0885380139388936
        ],
        [
          2050,
          0.0886514819996982
        ],
        [
          2051,
          0.088651590060727
        ],
        [
          2052,
          0.08865151791684919
        ]
      ]
    },
    {
      "seriesName": "INDNWS",
      "seriesValues": [
        [
          2019,
          2.3371983069466817
        ],
        [
          2020,
          2.1308623639042157
        ],
        [
          2021,
          2.2041624833494953
        ],
        [
          2022,
          2.182217927365291
        ],
        [
          2023,
          2.1602733747225455
        ],
        [
          2024,
          2.138328821979223
        ],
        [
          2025,
          2.116384269353271
        ],
        [
          2026,
          2.094439716500014
        ],
        [
          2027,
          2.072495132519027
        ],
        [
          2028,
          2.0505505820428924
        ],
        [
          2029,
          2.0286060317091317
        ],
        [
          2030,
          2.0066614502987417
        ],
        [
          2031,
          2.0092972993099973
        ],
        [
          2032,
          2.011933265499758
        ],
        [
          2033,
          2.0145692367353565
        ],
        [
          2034,
          2.017205208481931
        ],
        [
          2035,
          2.0198411802754523
        ],
        [
          2036,
          2.0224771508658614
        ],
        [
          2037,
          2.0251131284603163
        ],
        [
          2038,
          2.027749098977971
        ],
        [
          2039,
          2.0303850737225178
        ],
        [
          2040,
          2.0330210523323884
        ],
        [
          2041,
          2.0356570255214654
        ],
        [
          2042,
          2.038292987558673
        ],
        [
          2043,
          2.040928948567096
        ],
        [
          2044,
          2.043564931059581
        ],
        [
          2045,
          2.046200908793859
        ],
        [
          2046,
          2.0488368735726166
        ],
        [
          2047,
          2.0514728381857674
        ],
        [
          2048,
          2.054108799415973
        ],
        [
          2049,
          2.0567447645735437
        ],
        [
          2050,
          2.059380723861369
        ],
        [
          2051,
          2.0593807727121964
        ],
        [
          2052,
          2.059380726899708
        ]
      ]
    },
    {
      "seriesName": "INDRWS",
      "seriesValues": [
        [
          2019,
          1.6663534996654894
        ],
        [
          2020,
          1.7237490058852145
        ],
        [
          2021,
          1.9070632437081274
        ],
        [
          2022,
          1.8880765957519956
        ],
        [
          2023,
          1.8690899507715457
        ],
        [
          2024,
          1.8501033060546632
        ],
        [
          2025,
          1.831116661470157
        ],
        [
          2026,
          1.8121300166967642
        ],
        [
          2027,
          1.7931433407265092
        ],
        [
          2028,
          1.7741566983117796
        ],
        [
          2029,
          1.7551700560393004
        ],
        [
          2030,
          1.7361833819294306
        ],
        [
          2031,
          1.738463947828139
        ],
        [
          2032,
          1.7407446118572596
        ],
        [
          2033,
          1.7430252802638695
        ],
        [
          2034,
          1.7453059490839806
        ],
        [
          2035,
          1.7475866080174118
        ],
        [
          2036,
          1.7498672758682499
        ],
        [
          2037,
          1.752147950496463
        ],
        [
          2038,
          1.7544286182996252
        ],
        [
          2039,
          1.7567092900914634
        ],
        [
          2040,
          1.7589899662192718
        ],
        [
          2041,
          1.7612705997904259
        ],
        [
          2042,
          1.7635512812837624
        ],
        [
          2043,
          1.7658319672545213
        ],
        [
          2044,
          1.768112644844847
        ],
        [
          2045,
          1.7703933181544105
        ],
        [
          2046,
          1.7726739808138325
        ],
        [
          2047,
          1.7749546432941188
        ],
        [
          2048,
          1.7772353024929883
        ],
        [
          2049,
          1.7795159655938126
        ],
        [
          2050,
          1.7817965964424007
        ],
        [
          2051,
          1.7817966307230257
        ],
        [
          2052,
          1.7817965863937038
        ]
      ]
    },
    {
      "seriesName": "INDBGS",
      "seriesValues": [
        [
          2022,
          0.0465726801989286
        ],
        [
          2023,
          0.0742854107292638
        ],
        [
          2024,
          0.1021296735421465
        ],
        [
          2025,
          0.1317292679462661
        ],
        [
          2026,
          0.1725547731070553
        ],
        [
          2031,
          0.2622609888591702
        ],
        [
          2032,
          0.2815639370515231
        ],
        [
          2033,
          0.30855119091320593
        ],
        [
          2034,
          0.3339101384473417
        ],
        [
          2035,
          0.35368646828324424
        ],
        [
          2036,
          0.3722585524533828
        ],
        [
          2037,
          0.3928156750446443
        ],
        [
          2038,
          0.4286213369191226
        ],
        [
          2039,
          0.4621101764508879
        ],
        [
          2040,
          0.484626309510387
        ],
        [
          2041,
          0.506123497713512
        ],
        [
          2042,
          0.5263966512416207
        ],
        [
          2043,
          0.5460251295200388
        ],
        [
          2044,
          0.564907237951416
        ],
        [
          2045,
          0.5829893970803295
        ],
        [
          2046,
          0.6007415608476389
        ],
        [
          2047,
          0.6187964374448724
        ],
        [
          2048,
          0.6328610960688617
        ],
        [
          2049,
          0.6465260504020295
        ],
        [
          2050,
          0.6574325862818062
        ],
        [
          2051,
          0.607916414138271
        ],
        [
          2052,
          0.6479264644034819
        ]
      ]
    }
  ]
}