{
  "name": "mitigation_sectoralcbs-led_halfway",
  "data": [
    {
      "seriesName": "FT_IND",
      "seriesValues": [
        [
          2018,
          1.10595942930431
        ],
        [
          2019,
          1.27810994243544
        ],
        [
          2020,
          0.964615585035147
        ],
        [
          2021,
          1.00113042375455
        ],
        [
          2022,
          1.00449926023275
        ],
        [
          2023,
          1.00786843417252
        ],
        [
          2024,
          1.01123760721939
        ],
        [
          2025,
          1.01460678052016
        ],
        [
          2026,
          1.01797595759753
        ],
        [
          2027,
          1.021345332628
        ],
        [
          2028,
          1.02471451764079
        ],
        [
          2029,
          1.0280836820582
        ],
        [
          2030,
          1.03145286040899
        ],
        [
          2031,
          1.03522902748983
        ],
        [
          2032,
          1.03900528775002
        ],
        [
          2033,
          1.0427815487928
        ],
        [
          2034,
          1.04655781022
        ],
        [
          2035,
          1.05033407222556
        ],
        [
          2036,
          1.05411033554979
        ],
        [
          2037,
          1.05788664433995
        ],
        [
          2038,
          1.0616629135882
        ],
        [
          2039,
          1.06543905379408
        ],
        [
          2040,
          1.06921541907905
        ],
        [
          2041,
          1.07299156927419
        ],
        [
          2042,
          1.07676795436642
        ],
        [
          2043,
          1.0805442091929
        ],
        [
          2044,
          1.08432041707184
        ],
        [
          2045,
          1.08809657357967
        ],
        [
          2046,
          1.09187280412679
        ],
        [
          2047,
          1.0956490443357
        ],
        [
          2048,
          1.0994251627373
        ],
        [
          2049,
          1.10320140696934
        ],
        [
          2050,
          1.10697765092877
        ],
        [
          2051,
          1.10697806667917
        ],
        [
          2052,
          1.10697784034666
        ]
      ]
    },
    {
      "seriesName": "FT_SRV",
      "seriesValues": [
        [
          2018,
          0.026914737819377
        ],
        [
          2019,
          0.0241526066908617
        ],
        [
          2020,
          0.0260395290987344
        ],
        [
          2021,
          0.0245299911799748
        ],
        [
          2022,
          0.0049202306559263
        ],
        [
          2023,
          0.004612716215952
        ],
        [
          2024,
          0.0034608195704804
        ],
        [
          2025,
          0.001048669835882
        ],
        [
          2026,
          0.0036901730371478
        ],
        [
          2027,
          0.0033826586875399
        ],
        [
          2028,
          0.0030751445214755
        ],
        [
          2029,
          0.0027676301992329
        ],
        [
          2030,
          0.0002767056090696
        ],
        [
          2031,
          0.0021526020546811
        ],
        [
          2032,
          0.0018450875703595
        ],
        [
          2033,
          0.0015375735249314
        ],
        [
          2034,
          0.0012300587068813
        ],
        [
          2035,
          0.0005717233219266
        ]
      ]
    }
  ]
}