{
  "name": "mitigation_sectoralcbs-techoptimism",
  "data": [
    {
      "seriesName": "DMD_TRA-F-LAND",
      "seriesValues": [
        [
          2019,
          981.1285222618329
        ],
        [
          2020,
          57.414963334584066
        ],
        [
          2021,
          580.6820224570642
        ],
        [
          2022,
          573.5798209097774
        ],
        [
          2023,
          1266.0768007199974
        ],
        [
          2024,
          1588.599195902762
        ],
        [
          2025,
          1524.3982843123085
        ],
        [
          2026,
          1366.202041439601
        ],
        [
          2027,
          1539.9828178954251
        ],
        [
          2028,
          1507.3295937597659
        ],
        [
          2029,
          2167.6280291941575
        ],
        [
          2030,
          2062.828247641157
        ],
        [
          2031,
          863.9916950408099
        ],
        [
          2032,
          2566.6673439607157
        ],
        [
          2033,
          3220.909902425441
        ],
        [
          2034,
          3518.2453601896163
        ],
        [
          2035,
          3178.3580803743225
        ],
        [
          2036,
          3108.790512252235
        ],
        [
          2037,
          2739.379253943636
        ],
        [
          2038,
          2811.103283553724
        ],
        [
          2039,
          2633.9946694926857
        ],
        [
          2040,
          2278.0956437580994
        ],
        [
          2041,
          2327.1084484941557
        ],
        [
          2042,
          2351.1874283325933
        ],
        [
          2043,
          2531.690431350573
        ],
        [
          2044,
          2773.2914112800377
        ],
        [
          2045,
          2605.8826073500113
        ],
        [
          2046,
          2635.062069712982
        ],
        [
          2047,
          2603.70272027821
        ],
        [
          2048,
          2560.091179267975
        ],
        [
          2049,
          2631.683905532859
        ],
        [
          2050,
          2656.212011199174
        ],
        [
          2051,
          2388.5452828674565
        ]
      ]
    },
    {
      "seriesName": "DMD_TRA-P-LAND",
      "seriesValues": [
        [
          2019,
          406.04942132810737
        ],
        [
          2020,
          465.7447603086305
        ],
        [
          2021,
          2363.177175493376
        ],
        [
          2022,
          5442.368428774234
        ],
        [
          2023,
          3099.152807741078
        ],
        [
          2024,
          3115.620543669107
        ],
        [
          2025,
          2927.765534848163
        ],
        [
          2026,
          3481.3391057249196
        ],
        [
          2027,
          9518.8168491147
        ],
        [
          2028,
          10930.931381374869
        ],
        [
          2029,
          1218.5916735929427
        ],
        [
          2030,
          10.28279461832607
        ],
        [
          2031,
          11.205934624543422
        ],
        [
          2032,
          7839.83189235208
        ],
        [
          2033,
          8261.488667496524
        ],
        [
          2034,
          7776.246338729848
        ],
        [
          2035,
          6727.81810210327
        ],
        [
          2036,
          5551.366690119859
        ],
        [
          2037,
          5160.934248935249
        ],
        [
          2038,
          4275.420158178
        ],
        [
          2039,
          4021.6943363868736
        ],
        [
          2040,
          4050.8240687470347
        ],
        [
          2041,
          4566.274135300071
        ],
        [
          2042,
          5004.014487488689
        ],
        [
          2043,
          3804.9332481463557
        ],
        [
          2044,
          3660.4285493356247
        ],
        [
          2045,
          4144.199017021826
        ],
        [
          2046,
          3587.550279542073
        ],
        [
          2047,
          3695.5001257094573
        ],
        [
          2048,
          3255.2814701889647
        ],
        [
          2049,
          4143.203074895572
        ],
        [
          2050,
          4425.124257891678
        ],
        [
          2051,
          4389.759617143429
        ]
      ]
    }
  ]
}